cutmv/__init__.py
cutmv/cutmv.py
cutmv-0.0.4.dist-info/LICENSE
cutmv-0.0.4.dist-info/METADATA
cutmv-0.0.4.dist-info/WHEEL
cutmv-0.0.4.dist-info/top_level.txt
cutmv-0.0.4.dist-info/RECORD
