Metadata-Version: 2.1
Name: cutmv
Version: 0.0.4
Summary: small video cut tools
Home-page: https://gitee.com/QTDesign/cutmv
Author: Isaac
Author-email: gomehome@qq.com
License: UNKNOWN
Platform: UNKNOWN
Classifier: Programming Language :: Python :: 3
Classifier: License :: OSI Approved :: MIT License
Classifier: Operating System :: OS Independent
Requires-Python: >=3.7
